wasde_csv_client.py
my_wasde_package-0.1.1.dist-info/METADATA
my_wasde_package-0.1.1.dist-info/WHEEL
my_wasde_package-0.1.1.dist-info/top_level.txt
my_wasde_package-0.1.1.dist-info/RECORD
