Metadata-Version: 2.2
Name: my-wasde-package
Version: 0.1.1
Summary: A client for downloading and querying WASDE CSV data
Author-email: Your Name <you@example.com>
License: MIT
Keywords: WASDE,USDA,csv,client
Classifier: Programming Language :: Python :: 3
Classifier: License :: OSI Approved :: MIT License
Classifier: Operating System :: OS Independent
Requires-Python: >=3.7
